{"docno": "00010", "url": "https://give.ucdavis.edu/DDAG/341017-PAR", "simhash": 3306920204, "last-modified": "", "title": "Give UC Davis - UC Davis Parents Fund", "content": "give uc davi  uc davi parent fund way give whi give area support search result uc davi parent fund everi gift parent fund make differ  annual special gift uc davi parent fund donat fund uc davi parent fund your parent fund gift support all aspect student undergradu educ includ scholarship classroom upgrad studentrun project faculti award parent fund gift 1000 recogn davi chancellor club dcc inform eric gifford director develop parent give 530 7524903 phone categori fund purpos unrestrict fund type current offic univers develop uc davi shield avenu davi ca 956165270 phone 530 7544438 fax 530 7542294 connect support link uc davi copyright \u00a9 regent univers california davi campu all right reserv"}